{
  "project_info": {
    "project_number": "859628100199",
    "project_id": "flutter-533bc",
    "storage_bucket": "flutter-533bc.appspot.com"
  },
  "client": [
    {
      "client_info": {
        "mobilesdk_app_id": "1:859628100199:android:194ec062ba9ad718f892c2",
        "android_client_info": {
          "package_name": "com.example.firebase_app"
        }
      },
      "oauth_client": [],
      "api_key": [
        {
          "current_key": "AIzaSyAJpj3ajPzmT6U3NDoJhcWOk-g5vX8T81k"
        }
      ],
      "services": {
        "appinvite_service": {
          "other_platform_oauth_client": []
        }
      }
    }
  ],
  "configuration_version": "1"
}